LICENSE
xmppbot/__init__.py
xmppbot/basebot.py
xmppbot/cmdbot.py
xmppbot/common.py
xmppbot/configbot.py
xmppbot/timeout.py
xmppbot/xmppbot.py
xmppbot/xmppmsg.py
slixmppbot-2.0.4.dist-info/LICENSE
slixmppbot-2.0.4.dist-info/METADATA
slixmppbot-2.0.4.dist-info/WHEEL
slixmppbot-2.0.4.dist-info/RECORD
