Metadata-Version: 2.1
Name: slixmppbot
Version: 2.0.4
Summary: A framework for writing Jabber/XMPP bots
Home-page: https://github.com/s-nt-s/XmppBot
License: GPLv3
Keywords: xmpp,bot
Author: s-nt-s
Author-email: santos82h@gmail.com
Requires-Python: >=3.9,<4.0
Classifier: License :: OSI Approved :: GNU General Public License v3 (GPLv3)
Classifier: License :: Other/Proprietary License
Classifier: Operating System :: OS Independent
Classifier: Programming Language :: Python :: 3
Classifier: Programming Language :: Python :: 3.9
Classifier: Programming Language :: Python :: 3.10
Classifier: Programming Language :: Python :: 3.11
Classifier: Programming Language :: Python :: 3
Requires-Dist: PyYAML (>=6.0,<7.0)
Requires-Dist: slixmpp (>=1.8.3,<2.0.0)
